{"assets/data/calendar_100_years.json":["assets/data/calendar_100_years.json"],"assets/data/diagnosis_rules.json":["assets/data/diagnosis_rules.json"],"assets/data/elements.json":["assets/data/elements.json"],"assets/data/elements_data.json":["assets/data/elements_data.json"],"assets/data/samutthan_descriptions.json":["assets/data/samutthan_descriptions.json"],"assets/icon/logo.png":["assets/icon/logo.png"],"assets/images/image_fd8dda.png":["assets/images/image_fd8dda.png"],"packages/cupertino_icons/assets/CupertinoIcons.ttf":["packages/cupertino_icons/assets/CupertinoIcons.ttf"]}